sdk/__init__.py
sdk/sdk.py
sdk_package-0.1.0.dist-info/METADATA
sdk_package-0.1.0.dist-info/WHEEL
sdk_package-0.1.0.dist-info/top_level.txt
sdk_package-0.1.0.dist-info/RECORD
