Metadata-Version: 2.1
Name: sdk_package
Version: 0.1.0
Summary: A simple SDK for API key management and request handling
Home-page: https://github.com/yourusername/sdk_package
Author: Your Name
Author-email: your.email@example.com
Classifier: Programming Language :: Python :: 3
Classifier: License :: OSI Approved :: MIT License
Classifier: Operating System :: OS Independent
Requires-Python: >=3.6
